{
  "text": "【文本内容区域1】\n大学物理实验A(II)\n225043 物理实验中心 必修课\n1.5学分 36学时丨无 中文 考查",
  "file_path": "storage/images\\19c1e147d88a4b79afed5526e6374101_屏幕截图 2026-02-28 221316.png",
  "ocr": {
    "raw_text": "大学物理实验A(II)\n225043\n物理实验中心\n必修课\n1.5学分\n36学时丨无\n中文\n考查",
    "structured_text": "【文本内容区域1】\n大学物理实验A(II)\n225043 物理实验中心 必修课\n1.5学分 36学时丨无 中文 考查",
    "layout_type": "region_cluster",
    "modules": [
      {
        "module": "文本内容区域1",
        "text": "大学物理实验A(II)\n225043 物理实验中心 必修课\n1.5学分 36学时丨无 中文 考查",
        "blocks": [
          {
            "text": "大学物理实验A(II)",
            "confidence": 0.9473991394042969,
            "bbox": {
              "x1": 12.0,
              "y1": 122.0,
              "x2": 216.0,
              "y2": 158.0
            },
            "type": "text",
            "text_type": "normal_text",
            "low_confidence": false
          },
          {
            "text": "225043",
            "confidence": 0.9999725222587585,
            "bbox": {
              "x1": 12.0,
              "y1": 166.0,
              "x2": 87.0,
              "y2": 190.0
            },
            "type": "text",
            "text_type": "normal_text",
            "low_confidence": false
          },
          {
            "text": "物理实验中心",
            "confidence": 0.9997676014900208,
            "bbox": {
              "x1": 114.0,
              "y1": 166.0,
              "x2": 241.0,
              "y2": 190.0
            },
            "type": "text",
            "text_type": "handwriting_or_short_chinese",
            "low_confidence": false
          },
          {
            "text": "必修课",
            "confidence": 0.9994266033172607,
            "bbox": {
              "x1": 269.0,
              "y1": 165.0,
              "x2": 338.0,
              "y2": 192.0
            },
            "type": "text",
            "text_type": "handwriting_or_short_chinese",
            "low_confidence": false
          },
          {
            "text": "1.5学分",
            "confidence": 0.9999881982803345,
            "bbox": {
              "x1": 12.0,
              "y1": 198.0,
              "x2": 87.0,
              "y2": 224.0
            },
            "type": "text",
            "text_type": "normal_text",
            "low_confidence": false
          },
          {
            "text": "36学时丨无",
            "confidence": 0.8890268802642822,
            "bbox": {
              "x1": 113.0,
              "y1": 196.0,
              "x2": 242.0,
              "y2": 225.0
            },
            "type": "text",
            "text_type": "handwriting_or_short_chinese",
            "low_confidence": false
          },
          {
            "text": "中文",
            "confidence": 0.9998244047164917,
            "bbox": {
              "x1": 267.0,
              "y1": 199.0,
              "x2": 350.0,
              "y2": 222.0
            },
            "type": "text",
            "text_type": "handwriting_or_short_chinese",
            "low_confidence": false
          },
          {
            "text": "考查",
            "confidence": 0.9997354745864868,
            "bbox": {
              "x1": 340.0,
              "y1": 200.0,
              "x2": 387.0,
              "y2": 221.0
            },
            "type": "text",
            "text_type": "handwriting_or_short_chinese",
            "low_confidence": false
          }
        ],
        "bbox": {
          "x1": 12.0,
          "y1": 122.0,
          "x2": 387.0,
          "y2": 225.0
        }
      }
    ],
    "blocks": [
      {
        "text": "大学物理实验A(II)",
        "confidence": 0.9473991394042969,
        "bbox": {
          "x1": 12.0,
          "y1": 122.0,
          "x2": 216.0,
          "y2": 158.0
        },
        "type": "text",
        "text_type": "normal_text",
        "low_confidence": false
      },
      {
        "text": "225043",
        "confidence": 0.9999725222587585,
        "bbox": {
          "x1": 12.0,
          "y1": 166.0,
          "x2": 87.0,
          "y2": 190.0
        },
        "type": "text",
        "text_type": "normal_text",
        "low_confidence": false
      },
      {
        "text": "物理实验中心",
        "confidence": 0.9997676014900208,
        "bbox": {
          "x1": 114.0,
          "y1": 166.0,
          "x2": 241.0,
          "y2": 190.0
        },
        "type": "text",
        "text_type": "handwriting_or_short_chinese",
        "low_confidence": false
      },
      {
        "text": "必修课",
        "confidence": 0.9994266033172607,
        "bbox": {
          "x1": 269.0,
          "y1": 165.0,
          "x2": 338.0,
          "y2": 192.0
        },
        "type": "text",
        "text_type": "handwriting_or_short_chinese",
        "low_confidence": false
      },
      {
        "text": "1.5学分",
        "confidence": 0.9999881982803345,
        "bbox": {
          "x1": 12.0,
          "y1": 198.0,
          "x2": 87.0,
          "y2": 224.0
        },
        "type": "text",
        "text_type": "normal_text",
        "low_confidence": false
      },
      {
        "text": "36学时丨无",
        "confidence": 0.8890268802642822,
        "bbox": {
          "x1": 113.0,
          "y1": 196.0,
          "x2": 242.0,
          "y2": 225.0
        },
        "type": "text",
        "text_type": "handwriting_or_short_chinese",
        "low_confidence": false
      },
      {
        "text": "中文",
        "confidence": 0.9998244047164917,
        "bbox": {
          "x1": 267.0,
          "y1": 199.0,
          "x2": 350.0,
          "y2": 222.0
        },
        "type": "text",
        "text_type": "handwriting_or_short_chinese",
        "low_confidence": false
      },
      {
        "text": "考查",
        "confidence": 0.9997354745864868,
        "bbox": {
          "x1": 340.0,
          "y1": 200.0,
          "x2": 387.0,
          "y2": 221.0
        },
        "type": "text",
        "text_type": "handwriting_or_short_chinese",
        "low_confidence": false
      }
    ]
  },
  "visual_detection": {
    "has_visual": false,
    "reason": "主要内容为文字，使用文本模型分析",
    "text_area_ratio": 0.1397,
    "non_white_ratio": 0.0411
  },
  "ai_result": {
    "summary": "《大学物理实验A(II)》是面向本科生的必修实验课程，由物理实验中心开设，课程编号225043，共1.5学分、36学时，采用中文授课，考核方式为考查。",
    "entities": [
      {
        "name": "大学物理实验A(II)",
        "type": "课程",
        "description": "一门本科阶段的物理实验课程"
      },
      {
        "name": "225043",
        "type": "课程编号",
        "description": "该课程的唯一标识编码"
      },
      {
        "name": "物理实验中心",
        "type": "机构",
        "description": "负责开设和管理本实验课程的教学单位"
      },
      {
        "name": "必修课",
        "type": "课程性质",
        "description": "学生必须修读的课程类型"
      },
      {
        "name": "1.5学分",
        "type": "学分",
        "description": "课程对应的学分值"
      },
      {
        "name": "36学时",
        "type": "学时",
        "description": "课程总教学时长"
      },
      {
        "name": "中文",
        "type": "语言",
        "description": "课程授课所使用的语言"
      },
      {
        "name": "考查",
        "type": "考核方式",
        "description": "课程的考核形式，非考试类"
      }
    ],
    "relations": [
      {
        "source": "大学物理实验A(II)",
        "target": "225043",
        "relation": "具有课程编号",
        "confidence": 0.95
      },
      {
        "source": "大学物理实验A(II)",
        "target": "物理实验中心",
        "relation": "由...开设",
        "confidence": 0.95
      },
      {
        "source": "大学物理实验A(II)",
        "target": "必修课",
        "relation": "课程性质为",
        "confidence": 0.95
      },
      {
        "source": "大学物理实验A(II)",
        "target": "1.5学分",
        "relation": "对应学分为",
        "confidence": 0.95
      },
      {
        "source": "大学物理实验A(II)",
        "target": "36学时",
        "relation": "总学时为",
        "confidence": 0.95
      },
      {
        "source": "大学物理实验A(II)",
        "target": "中文",
        "relation": "授课语言为",
        "confidence": 0.95
      },
      {
        "source": "大学物理实验A(II)",
        "target": "考查",
        "relation": "考核方式为",
        "confidence": 0.95
      }
    ],
    "keywords": [
      "大学物理实验A(II)",
      "物理实验中心",
      "必修课",
      "1.5学分",
      "36学时",
      "中文",
      "考查"
    ],
    "modules": [
      {
        "module": "课程基本信息",
        "text": "大学物理实验A(II)\n课程编号：225043\n开课单位：物理实验中心\n课程性质：必修课\n学分：1.5\n学时：36\n授课语言：中文\n考核方式：考查"
      }
    ],
    "visual_notes": [],
    "visual_detection": {
      "has_visual": false,
      "reason": "主要内容为文字，使用文本模型分析",
      "text_area_ratio": 0.1397,
      "non_white_ratio": 0.0411
    }
  },
  "graph": null
}